{
  "highStakesWithdrawalCount": 0,
  "_id": "668bf97d67240f8bd157008a",
  "userId": "c7e984df-d505-4af2-95cf-148d0bc64880",
  "orderId": "1037478",
  "programId": "65eebdfa9ca56cbf515b5d2c",
  "tsAccount": "24186432",
  "tsAccountId": "24186432",
  "tsUserId": "24186432",
  "tradingSystem": "meta-trader-5",
  "status": "disabled",
  "type": "evaluation",
  "state": {
    "terminated": true,
    "dailyPause": false,
    "dailyLoss": false,
    "target": false,
    "expired": false
  },
  "boosters": [],
  "level": 1,
  "creationRetries": 0,
  "createdAt": "2024-07-08T14:36:45.698Z",
  "updatedAt": "2024-07-08T14:36:45.698Z",
  "config": {
    "hasSeen": true
  },
  "purchaseId": "1037478",
  "assetClass": "forex",
  "accountId": "24186432",
  "name": "EVALUATION 24186432",
  "balance": 17969.35,
  "equity": 17969.35,
  "pnl": -2030.649999999997,
  "stats": {
    "_id": "6a3d4485723d3851222ffefe",
    "accountId": "24186432",
    "avgLoss": -23.400505050505018,
    "avgProfit": 71.5,
    "avgTradeDuration": 1356909.8058252428,
    "avgTradeSize": 0.13398058252427159,
    "bestProfit": 85.5,
    "biggestLoss": -264,
    "createdAt": "2026-06-25T15:08:53.962Z",
    "expectancy": -19.71504854368929,
    "grossLoss": -2316.649999999997,
    "grossProfit": 286,
    "latestPositionDate": "2024-07-08T14:36:47.579Z",
    "longTrades": 66,
    "lossTrades": 99,
    "profitBySymbol": {
      "XAUUSD": -2030.6499999999999
    },
    "profitFactor": 0.12345412556924887,
    "profitTrades": 4,
    "shortTrades": 37,
    "totalFees": -55.19999999999989,
    "totalNetProfit": -2030.649999999997,
    "totalPositionDuration": 139761710,
    "totalQuantity": 13.799999999999972,
    "totalRebatedFees": 0,
    "totalTrades": 103,
    "updatedAt": "2026-06-25T15:08:53.962Z",
    "winRate": 0.038834951456310676
  },
  "balanceDetails": {
    "unrealized": 0,
    "balance": 17969.35,
    "baseBalance": 5000,
    "credits": 0,
    "profitCredits": 0,
    "refundCredits": 0,
    "equity": 17969.35,
    "maxLoss": 250,
    "profitAndLoss": -2030.65,
    "dailyProfitAndLoss": 0,
    "weeklyProfitAndLoss": 0,
    "invalidProfitAndLoss": 0,
    "snapshotEquity": 19003.05,
    "snapshotBalance": 19003.05,
    "allowedDailyLosses": -19003.05,
    "syncDate": "2024-07-08T14:36:48.725Z",
    "consecutiveInactivityDays": 0,
    "highWaterMark": 0,
    "growthPercentage": -40.613,
    "highWaterMarkPnl": 2969.35
  },
  "trades": [
    {
      "sl": 0,
      "tp": 0,
      "pips": 0,
      "pipValue": 0,
      "_id": "668bf9808259f96327d3f127",
      "accountId": "24186432",
      "externalId": "246197734",
      "closeDate": "2024-06-18T15:16:15.718Z",
      "comment": "[so 140.68$/17978.15/12779.47]",
      "createdAt": "2024-07-08T14:36:47.639Z",
      "entry": 2323.73,
      "exit": 2323.05,
      "fee": -0.4,
      "invalidReasons": [],
      "isClosed": true,
      "isPartial": false,
      "isValid": true,
      "openDate": "2024-06-18T15:15:40.814Z",
      "profitAndLoss": -7.2,
      "quantity": 0.1,
      "side": "Buy",
      "swap": 0,
      "symbol": "XAUUSD",
      "updatedAt": "2024-07-08T14:36:47.728Z",
      "id": "246197734",
      "date": "2024-06-18T15:15:40.814Z"
    },
    {
      "sl": 0,
      "tp": 0,
      "pips": 0,
      "pipValue": 0,
      "_id": "668bf9808259f96327d3f126",
      "externalId": "246197730",
      "accountId": "24186432",
      "closeDate": "2024-06-18T15:16:15.707Z",
      "comment": "[so 134.57$/17978.55/13360.40]",
      "createdAt": "2024-07-08T14:36:47.641Z",
      "entry": 2323.73,
      "exit": 2323.05,
      "fee": -0.4,
      "invalidReasons": [],
      "isClosed": true,
      "isPartial": false,
      "isValid": true,
      "openDate": "2024-06-18T15:15:40.265Z",
      "profitAndLoss": -7.2,
      "quantity": 0.1,
      "side": "Buy",
      "swap": 0,
      "symbol": "XAUUSD",
      "updatedAt": "2024-07-08T14:36:47.699Z",
      "id": "246197730",
      "date": "2024-06-18T15:15:40.265Z"
    },
    {
      "sl": 0,
      "tp": 0,
      "pips": 0,
      "pipValue": 0,
      "_id": "668bf9808259f96327d3f69a",
      "accountId": "24186432",
      "externalId": "246197726",
      "closeDate": "2024-06-18T15:16:15.718Z",
      "comment": "End Program",
      "createdAt": "2024-07-08T14:36:47.734Z",
      "entry": 2323.68,
      "exit": 2323.05,
      "fee": -0.4,
      "invalidReasons": [],
      "isClosed": true,
      "isPartial": false,
      "isValid": true,
      "openDate": "2024-06-18T15:15:40.014Z",
      "profitAndLoss": -6.7,
      "quantity": 0.1,
      "side": "Buy",
      "swap": 0,
      "symbol": "XAUUSD",
      "updatedAt": "2024-07-08T14:36:47.697Z",
      "id": "246197726",
      "date": "2024-06-18T15:15:40.014Z"
    },
    {
      "sl": 0,
      "tp": 0,
      "pips": 0,
      "pipValue": 0,
      "_id": "668bf9808259f96327d3f45f",
      "accountId": "24186432",
      "externalId": "246197400",
      "closeDate": "2024-06-18T15:16:15.717Z",
      "comment": "End Program",
      "createdAt": "2024-07-08T14:36:47.685Z",
      "entry": 2323.63,
      "exit": 2323.05,
      "fee": -0.4,
      "invalidReasons": [],
      "isClosed": true,
      "isPartial": false,
      "isValid": true,
      "openDate": "2024-06-18T15:15:05.815Z",
      "profitAndLoss": -6.2,
      "quantity": 0.1,
      "side": "Buy",
      "swap": 0,
      "symbol": "XAUUSD",
      "updatedAt": "2024-07-08T14:36:47.696Z",
      "id": "246197400",
      "date": "2024-06-18T15:15:05.815Z"
    },
    {
      "sl": 0,
      "tp": 0,
      "pips": 0,
      "pipValue": 0,
      "_id": "668bf9808259f96327d3f4cb",
      "accountId": "24186432",
      "externalId": "246197388",
      "closeDate": "2024-06-18T15:16:15.717Z",
      "comment": "End Program",
      "createdAt": "2024-07-08T14:36:47.713Z",
      "entry": 2323.67,
      "exit": 2323.05,
      "fee": -0.4,
      "invalidReasons": [],
      "isClosed": true,
      "isPartial": false,
      "isValid": true,
      "openDate": "2024-06-18T15:15:05.102Z",
      "profitAndLoss": -6.6000000000000005,
      "quantity": 0.1,
      "side": "Buy",
      "swap": 0,
      "symbol": "XAUUSD",
      "updatedAt": "2024-07-08T14:36:47.698Z",
      "id": "246197388",
      "date": "2024-06-18T15:15:05.102Z"
    },
    {
      "sl": 0,
      "tp": 0,
      "pips": 0,
      "pipValue": 0,
      "_id": "668bf9808259f96327d3f5b2",
      "accountId": "24186432",
      "externalId": "246197386",
      "closeDate": "2024-06-18T15:16:15.717Z",
      "comment": "End Program",
      "createdAt": "2024-07-08T14:36:47.719Z",
      "entry": 2323.68,
      "exit": 2323.05,
      "fee": -0.4,
      "invalidReasons": [],
      "isClosed": true,
      "isPartial": false,
      "isValid": true,
      "openDate": "2024-06-18T15:15:04.915Z",
      "profitAndLoss": -6.7,
      "quantity": 0.1,
      "side": "Buy",
      "swap": 0,
      "symbol": "XAUUSD",
      "updatedAt": "2024-07-08T14:36:47.695Z",
      "id": "246197386",
      "date": "2024-06-18T15:15:04.915Z"
    },
    {
      "sl": 0,
      "tp": 0,
      "pips": 0,
      "pipValue": 0,
      "_id": "668bf9808259f96327d3f495",
      "accountId": "24186432",
      "externalId": "246197382",
      "closeDate": "2024-06-18T15:16:15.716Z",
      "comment": "End Program",
      "createdAt": "2024-07-08T14:36:47.709Z",
      "entry": 2323.67,
      "exit": 2323.05,
      "fee": -0.4,
      "invalidReasons": [],
      "isClosed": true,
      "isPartial": false,
      "isValid": true,
      "openDate": "2024-06-18T15:15:04.731Z",
      "profitAndLoss": -6.6000000000000005,
      "quantity": 0.1,
      "side": "Buy",
      "swap": 0,
      "symbol": "XAUUSD",
      "updatedAt": "2024-07-08T14:36:47.698Z",
      "id": "246197382",
      "date": "2024-06-18T15:15:04.731Z"
    },
    {
      "sl": 0,
      "tp": 0,
      "pips": 0,
      "pipValue": 0,
      "_id": "668bf9808259f96327d3f3a1",
      "accountId": "24186432",
      "externalId": "246197381",
      "closeDate": "2024-06-18T15:16:15.716Z",
      "comment": "End Program",
      "createdAt": "2024-07-08T14:36:47.699Z",
      "entry": 2323.67,
      "exit": 2323.05,
      "fee": -0.4,
      "invalidReasons": [],
      "isClosed": true,
      "isPartial": false,
      "isValid": true,
      "openDate": "2024-06-18T15:15:04.531Z",
      "profitAndLoss": -6.6000000000000005,
      "quantity": 0.1,
      "side": "Buy",
      "swap": 0,
      "symbol": "XAUUSD",
      "updatedAt": "2024-07-08T14:36:47.707Z",
      "id": "246197381",
      "date": "2024-06-18T15:15:04.531Z"
    },
    {
      "sl": 0,
      "tp": 0,
      "pips": 0,
      "pipValue": 0,
      "_id": "668bf9808259f96327d3f4aa",
      "accountId": "24186432",
      "externalId": "246197379",
      "closeDate": "2024-06-18T15:16:15.716Z",
      "comment": "End Program",
      "createdAt": "2024-07-08T14:36:47.711Z",
      "entry": 2323.67,
      "exit": 2323.05,
      "fee": -0.4,
      "invalidReasons": [],
      "isClosed": true,
      "isPartial": false,
      "isValid": true,
      "openDate": "2024-06-18T15:15:04.331Z",
      "profitAndLoss": -6.6000000000000005,
      "quantity": 0.1,
      "side": "Buy",
      "swap": 0,
      "symbol": "XAUUSD",
      "updatedAt": "2024-07-08T14:36:47.694Z",
      "id": "246197379",
      "date": "2024-06-18T15:15:04.331Z"
    },
    {
      "sl": 0,
      "tp": 0,
      "pips": 0,
      "pipValue": 0,
      "_id": "668bf9808259f96327d3f577",
      "accountId": "24186432",
      "externalId": "246197372",
      "closeDate": "2024-06-18T15:16:15.715Z",
      "comment": "End Program",
      "createdAt": "2024-07-08T14:36:47.715Z",
      "entry": 2323.65,
      "exit": 2323.05,
      "fee": -0.4,
      "invalidReasons": [],
      "isClosed": true,
      "isPartial": false,
      "isValid": true,
      "openDate": "2024-06-18T15:15:04.148Z",
      "profitAndLoss": -6.4,
      "quantity": 0.1,
      "side": "Buy",
      "swap": 0,
      "symbol": "XAUUSD",
      "updatedAt": "2024-07-08T14:36:47.691Z",
      "id": "246197372",
      "date": "2024-06-18T15:15:04.148Z"
    },
    {
      "sl": 0,
      "tp": 0,
      "pips": 0,
      "pipValue": 0,
      "_id": "668bf9808259f96327d3ef79",
      "externalId": "246197369",
      "accountId": "24186432",
      "closeDate": "2024-06-18T15:16:15.715Z",
      "comment": "End Program",
      "createdAt": "2024-07-08T14:36:47.619Z",
      "entry": 2323.64,
      "exit": 2323.05,
      "fee": -0.4,
      "invalidReasons": [],
      "isClosed": true,
      "isPartial": false,
      "isValid": true,
      "openDate": "2024-06-18T15:15:03.949Z",
      "profitAndLoss": -6.300000000000001,
      "quantity": 0.1,
      "side": "Buy",
      "swap": 0,
      "symbol": "XAUUSD",
      "updatedAt": "2024-07-08T14:36:47.693Z",
      "id": "246197369",
      "date": "2024-06-18T15:15:03.949Z"
    },
    {
      "sl": 0,
      "tp": 0,
      "pips": 0,
      "pipValue": 0,
      "_id": "668bf9808259f96327d3f172",
      "accountId": "24186432",
      "externalId": "246197359",
      "closeDate": "2024-06-18T15:16:15.714Z",
      "comment": "End Program",
      "createdAt": "2024-07-08T14:36:47.651Z",
      "entry": 2323.63,
      "exit": 2323.05,
      "fee": -0.4,
      "invalidReasons": [],
      "isClosed": true,
      "isPartial": false,
      "isValid": true,
      "openDate": "2024-06-18T15:15:03.580Z",
      "profitAndLoss": -6.2,
      "quantity": 0.1,
      "side": "Buy",
      "swap": 0,
      "symbol": "XAUUSD",
      "updatedAt": "2024-07-08T14:36:47.692Z",
      "id": "246197359",
      "date": "2024-06-18T15:15:03.580Z"
    },
    {
      "sl": 0,
      "tp": 0,
      "pips": 0,
      "pipValue": 0,
      "_id": "668bf9808259f96327d3f113",
      "accountId": "24186432",
      "externalId": "246197354",
      "closeDate": "2024-06-18T15:16:15.714Z",
      "comment": "End Program",
      "createdAt": "2024-07-08T14:36:47.648Z",
      "entry": 2323.5,
      "exit": 2323.05,
      "fee": -0.4,
      "invalidReasons": [],
      "isClosed": true,
      "isPartial": false,
      "isValid": true,
      "openDate": "2024-06-18T15:15:03.348Z",
      "profitAndLoss": -4.9,
      "quantity": 0.1,
      "side": "Buy",
      "swap": 0,
      "symbol": "XAUUSD",
      "updatedAt": "2024-07-08T14:36:47.693Z",
      "id": "246197354",
      "date": "2024-06-18T15:15:03.348Z"
    },
    {
      "sl": 0,
      "tp": 0,
      "pips": 0,
      "pipValue": 0,
      "_id": "668bf9808259f96327d3f0ec",
      "accountId": "24186432",
      "externalId": "246197350",
      "closeDate": "2024-06-18T15:16:15.714Z",
      "comment": "End Program",
      "createdAt": "2024-07-08T14:36:47.645Z",
      "entry": 2323.5,
      "exit": 2323.05,
      "fee": -0.4,
      "invalidReasons": [],
      "isClosed": true,
      "isPartial": false,
      "isValid": true,
      "openDate": "2024-06-18T15:15:03.146Z",
      "profitAndLoss": -4.9,
      "quantity": 0.1,
      "side": "Buy",
      "swap": 0,
      "symbol": "XAUUSD",
      "updatedAt": "2024-07-08T14:36:47.658Z",
      "id": "246197350",
      "date": "2024-06-18T15:15:03.146Z"
    },
    {
      "sl": 0,
      "tp": 0,
      "pips": 0,
      "pipValue": 0,
      "_id": "668bf97f8259f96327d3ee8e",
      "accountId": "24186432",
      "externalId": "246197345",
      "closeDate": "2024-06-18T15:16:15.713Z",
      "comment": "End Program",
      "createdAt": "2024-07-08T14:36:47.610Z",
      "entry": 2323.49,
      "exit": 2323.05,
      "fee": -0.4,
      "invalidReasons": [],
      "isClosed": true,
      "isPartial": false,
      "isValid": true,
      "openDate": "2024-06-18T15:15:02.897Z",
      "profitAndLoss": -4.800000000000001,
      "quantity": 0.1,
      "side": "Buy",
      "swap": 0,
      "symbol": "XAUUSD",
      "updatedAt": "2024-07-08T14:36:47.618Z",
      "id": "246197345",
      "date": "2024-06-18T15:15:02.897Z"
    },
    {
      "sl": 0,
      "tp": 0,
      "pips": 0,
      "pipValue": 0,
      "_id": "668bf9808259f96327d3f26e",
      "externalId": "246197342",
      "accountId": "24186432",
      "closeDate": "2024-06-18T15:16:15.713Z",
      "comment": "End Program",
      "createdAt": "2024-07-08T14:36:47.657Z",
      "entry": 2323.49,
      "exit": 2323.05,
      "fee": -0.4,
      "invalidReasons": [],
      "isClosed": true,
      "isPartial": false,
      "isValid": true,
      "openDate": "2024-06-18T15:15:02.697Z",
      "profitAndLoss": -4.800000000000001,
      "quantity": 0.1,
      "side": "Buy",
      "swap": 0,
      "symbol": "XAUUSD",
      "updatedAt": "2024-07-08T14:36:47.672Z",
      "id": "246197342",
      "date": "2024-06-18T15:15:02.697Z"
    },
    {
      "sl": 0,
      "tp": 0,
      "pips": 0,
      "pipValue": 0,
      "_id": "668bf9808259f96327d3f18c",
      "accountId": "24186432",
      "externalId": "246197334",
      "closeDate": "2024-06-18T15:16:15.712Z",
      "comment": "End Program",
      "createdAt": "2024-07-08T14:36:47.646Z",
      "entry": 2323.47,
      "exit": 2323.05,
      "fee": -0.4,
      "invalidReasons": [],
      "isClosed": true,
      "isPartial": false,
      "isValid": true,
      "openDate": "2024-06-18T15:15:02.465Z",
      "profitAndLoss": -4.6000000000000005,
      "quantity": 0.1,
      "side": "Buy",
      "swap": 0,
      "symbol": "XAUUSD",
      "updatedAt": "2024-07-08T14:36:47.656Z",
      "id": "246197334",
      "date": "2024-06-18T15:15:02.465Z"
    },
    {
      "sl": 0,
      "tp": 0,
      "pips": 0,
      "pipValue": 0,
      "_id": "668bf97f8259f96327d3ecc8",
      "accountId": "24186432",
      "externalId": "246197245",
      "closeDate": "2024-06-18T15:16:15.711Z",
      "comment": "End Program",
      "createdAt": "2024-07-08T14:36:47.581Z",
      "entry": 2323.37,
      "exit": 2323.05,
      "fee": -0.4,
      "invalidReasons": [],
      "isClosed": true,
      "isPartial": false,
      "isValid": true,
      "openDate": "2024-06-18T15:14:55.975Z",
      "profitAndLoss": -3.6,
      "quantity": 0.1,
      "side": "Buy",
      "swap": 0,
      "symbol": "XAUUSD",
      "updatedAt": "2024-07-08T14:36:47.647Z",
      "id": "246197245",
      "date": "2024-06-18T15:14:55.975Z"
    },
    {
      "sl": 0,
      "tp": 0,
      "pips": 0,
      "pipValue": 0,
      "_id": "668bf9808259f96327d3ef5a",
      "externalId": "246197242",
      "accountId": "24186432",
      "closeDate": "2024-06-18T15:16:15.710Z",
      "comment": "End Program",
      "createdAt": "2024-07-08T14:36:47.615Z",
      "entry": 2323.37,
      "exit": 2323.05,
      "fee": -0.4,
      "invalidReasons": [],
      "isClosed": true,
      "isPartial": false,
      "isValid": true,
      "openDate": "2024-06-18T15:14:55.396Z",
      "profitAndLoss": -3.6,
      "quantity": 0.1,
      "side": "Buy",
      "swap": 0,
      "symbol": "XAUUSD",
      "updatedAt": "2024-07-08T14:36:47.625Z",
      "id": "246197242",
      "date": "2024-06-18T15:14:55.396Z"
    },
    {
      "sl": 0,
      "tp": 0,
      "pips": 0,
      "pipValue": 0,
      "_id": "668bf9808259f96327d3f208",
      "accountId": "24186432",
      "externalId": "246197233",
      "closeDate": "2024-06-18T15:16:15.710Z",
      "comment": "End Program",
      "createdAt": "2024-07-08T14:36:47.653Z",
      "entry": 2323.38,
      "exit": 2323.05,
      "fee": -0.4,
      "invalidReasons": [],
      "isClosed": true,
      "isPartial": false,
      "isValid": true,
      "openDate": "2024-06-18T15:14:54.157Z",
      "profitAndLoss": -3.6999999999999997,
      "quantity": 0.1,
      "side": "Buy",
      "swap": 0,
      "symbol": "XAUUSD",
      "updatedAt": "2024-07-08T14:36:47.667Z",
      "id": "246197233",
      "date": "2024-06-18T15:14:54.157Z"
    },
    {
      "sl": 0,
      "tp": 0,
      "pips": 0,
      "pipValue": 0,
      "_id": "668bf9808259f96327d3f1e1",
      "externalId": "246197230",
      "accountId": "24186432",
      "closeDate": "2024-06-18T15:16:15.709Z",
      "comment": "End Program",
      "createdAt": "2024-07-08T14:36:47.655Z",
      "entry": 2323.37,
      "exit": 2323.05,
      "fee": -0.4,
      "invalidReasons": [],
      "isClosed": true,
      "isPartial": false,
      "isValid": true,
      "openDate": "2024-06-18T15:14:53.724Z",
      "profitAndLoss": -3.6,
      "quantity": 0.1,
      "side": "Buy",
      "swap": 0,
      "symbol": "XAUUSD",
      "updatedAt": "2024-07-08T14:36:47.652Z",
      "id": "246197230",
      "date": "2024-06-18T15:14:53.724Z"
    },
    {
      "sl": 0,
      "tp": 0,
      "pips": 0,
      "pipValue": 0,
      "_id": "668bf9808259f96327d3ef70",
      "accountId": "24186432",
      "externalId": "246197191",
      "closeDate": "2024-06-18T15:16:15.709Z",
      "comment": "End Program",
      "createdAt": "2024-07-08T14:36:47.617Z",
      "entry": 2323.33,
      "exit": 2323.05,
      "fee": -0.4,
      "invalidReasons": [],
      "isClosed": true,
      "isPartial": false,
      "isValid": true,
      "openDate": "2024-06-18T15:14:50.505Z",
      "profitAndLoss": -3.1999999999999997,
      "quantity": 0.1,
      "side": "Buy",
      "swap": 0,
      "symbol": "XAUUSD",
      "updatedAt": "2024-07-08T14:36:47.668Z",
      "id": "246197191",
      "date": "2024-06-18T15:14:50.505Z"
    },
    {
      "sl": 0,
      "tp": 0,
      "pips": 0,
      "pipValue": 0,
      "_id": "668bf9808259f96327d3ef85",
      "accountId": "24186432",
      "externalId": "246197184",
      "closeDate": "2024-06-18T15:16:15.708Z",
      "comment": "End Program",
      "createdAt": "2024-07-08T14:36:47.616Z",
      "entry": 2323.27,
      "exit": 2323.05,
      "fee": -0.4,
      "invalidReasons": [],
      "isClosed": true,
      "isPartial": false,
      "isValid": true,
      "openDate": "2024-06-18T15:14:49.388Z",
      "profitAndLoss": -2.6,
      "quantity": 0.1,
      "side": "Buy",
      "swap": 0,
      "symbol": "XAUUSD",
      "updatedAt": "2024-07-08T14:36:47.625Z",
      "id": "246197184",
      "date": "2024-06-18T15:14:49.388Z"
    },
    {
      "sl": 0,
      "tp": 0,
      "pips": 0,
      "pipValue": 0,
      "_id": "668bf9808259f96327d3f185",
      "externalId": "246191045",
      "accountId": "24186432",
      "closeDate": "2024-06-18T15:13:55.273Z",
      "comment": "",
      "createdAt": "2024-07-08T14:36:47.648Z",
      "entry": 2321.69,
      "exit": 2322.67,
      "fee": -0.4,
      "invalidReasons": [],
      "isClosed": true,
      "isPartial": false,
      "isValid": true,
      "openDate": "2024-06-18T15:04:56.345Z",
      "profitAndLoss": -10.200000000000001,
      "quantity": 0.1,
      "side": "Sell",
      "swap": 0,
      "symbol": "XAUUSD",
      "updatedAt": "2024-07-08T14:36:47.653Z",
      "id": "246191045",
      "date": "2024-06-18T15:04:56.345Z"
    },
    {
      "sl": 0,
      "tp": 0,
      "pips": 0,
      "pipValue": 0,
      "_id": "668bf9808259f96327d3f1ad",
      "accountId": "24186432",
      "externalId": "246191043",
      "closeDate": "2024-06-18T15:13:55.241Z",
      "comment": "",
      "createdAt": "2024-07-08T14:36:47.651Z",
      "entry": 2321.69,
      "exit": 2322.67,
      "fee": -0.4,
      "invalidReasons": [],
      "isClosed": true,
      "isPartial": false,
      "isValid": true,
      "openDate": "2024-06-18T15:04:56.129Z",
      "profitAndLoss": -10.200000000000001,
      "quantity": 0.1,
      "side": "Sell",
      "swap": 0,
      "symbol": "XAUUSD",
      "updatedAt": "2024-07-08T14:36:47.697Z",
      "id": "246191043",
      "date": "2024-06-18T15:04:56.129Z"
    },
    {
      "sl": 0,
      "tp": 0,
      "pips": 0,
      "pipValue": 0,
      "_id": "668bf97f8259f96327d3ecb9",
      "accountId": "24186432",
      "externalId": "246191040",
      "closeDate": "2024-06-18T15:13:55.241Z",
      "comment": "",
      "createdAt": "2024-07-08T14:36:47.564Z",
      "entry": 2321.69,
      "exit": 2322.67,
      "fee": -0.4,
      "invalidReasons": [],
      "isClosed": true,
      "isPartial": false,
      "isValid": true,
      "openDate": "2024-06-18T15:04:55.952Z",
      "profitAndLoss": -10.200000000000001,
      "quantity": 0.1,
      "side": "Sell",
      "swap": 0,
      "symbol": "XAUUSD",
      "updatedAt": "2024-07-08T14:36:47.592Z",
      "id": "246191040",
      "date": "2024-06-18T15:04:55.952Z"
    },
    {
      "sl": 0,
      "tp": 0,
      "pips": 0,
      "pipValue": 0,
      "_id": "668bf9808259f96327d3ef86",
      "accountId": "24186432",
      "externalId": "246191039",
      "closeDate": "2024-06-18T15:13:55.230Z",
      "comment": "",
      "createdAt": "2024-07-08T14:36:47.621Z",
      "entry": 2321.69,
      "exit": 2322.67,
      "fee": -0.4,
      "invalidReasons": [],
      "isClosed": true,
      "isPartial": false,
      "isValid": true,
      "openDate": "2024-06-18T15:04:55.786Z",
      "profitAndLoss": -10.200000000000001,
      "quantity": 0.1,
      "side": "Sell",
      "swap": 0,
      "symbol": "XAUUSD",
      "updatedAt": "2024-07-08T14:36:47.642Z",
      "id": "246191039",
      "date": "2024-06-18T15:04:55.786Z"
    },
    {
      "sl": 0,
      "tp": 0,
      "pips": 0,
      "pipValue": 0,
      "_id": "668bf9808259f96327d3ef3a",
      "accountId": "24186432",
      "externalId": "246191037",
      "closeDate": "2024-06-18T15:13:55.230Z",
      "comment": "",
      "createdAt": "2024-07-08T14:36:47.591Z",
      "entry": 2321.69,
      "exit": 2322.67,
      "fee": -0.4,
      "invalidReasons": [],
      "isClosed": true,
      "isPartial": false,
      "isValid": true,
      "openDate": "2024-06-18T15:04:55.578Z",
      "profitAndLoss": -10.200000000000001,
      "quantity": 0.1,
      "side": "Sell",
      "swap": 0,
      "symbol": "XAUUSD",
      "updatedAt": "2024-07-08T14:36:47.655Z",
      "id": "246191037",
      "date": "2024-06-18T15:04:55.578Z"
    },
    {
      "sl": 0,
      "tp": 0,
      "pips": 0,
      "pipValue": 0,
      "_id": "668bf9808259f96327d3ef81",
      "externalId": "246191034",
      "accountId": "24186432",
      "closeDate": "2024-06-18T15:13:55.230Z",
      "comment": "",
      "createdAt": "2024-07-08T14:36:47.620Z",
      "entry": 2321.67,
      "exit": 2322.67,
      "fee": -0.4,
      "invalidReasons": [],
      "isClosed": true,
      "isPartial": false,
      "isValid": true,
      "openDate": "2024-06-18T15:04:55.365Z",
      "profitAndLoss": -10.4,
      "quantity": 0.1,
      "side": "Sell",
      "swap": 0,
      "symbol": "XAUUSD",
      "updatedAt": "2024-07-08T14:36:47.877Z",
      "id": "246191034",
      "date": "2024-06-18T15:04:55.365Z"
    },
    {
      "sl": 0,
      "tp": 0,
      "pips": 0,
      "pipValue": 0,
      "_id": "668bf9808259f96327d3ef97",
      "externalId": "246190959",
      "accountId": "24186432",
      "closeDate": "2024-06-18T15:13:55.230Z",
      "comment": "",
      "createdAt": "2024-07-08T14:36:47.623Z",
      "entry": 2321.58,
      "exit": 2322.67,
      "fee": -0.4,
      "invalidReasons": [],
      "isClosed": true,
      "isPartial": false,
      "isValid": true,
      "openDate": "2024-06-18T15:04:46.176Z",
      "profitAndLoss": -11.3,
      "quantity": 0.1,
      "side": "Sell",
      "swap": 0,
      "symbol": "XAUUSD",
      "updatedAt": "2024-07-08T14:36:47.873Z",
      "id": "246190959",
      "date": "2024-06-18T15:04:46.176Z"
    },
    {
      "sl": 0,
      "tp": 0,
      "pips": 0,
      "pipValue": 0,
      "_id": "668bf9808259f96327d3ef32",
      "accountId": "24186432",
      "externalId": "246190957",
      "closeDate": "2024-06-18T15:13:55.230Z",
      "comment": "",
      "createdAt": "2024-07-08T14:36:47.590Z",
      "entry": 2321.63,
      "exit": 2322.67,
      "fee": -0.4,
      "invalidReasons": [],
      "isClosed": true,
      "isPartial": false,
      "isValid": true,
      "openDate": "2024-06-18T15:04:45.998Z",
      "profitAndLoss": -10.8,
      "quantity": 0.1,
      "side": "Sell",
      "swap": 0,
      "symbol": "XAUUSD",
      "updatedAt": "2024-07-08T14:36:47.887Z",
      "id": "246190957",
      "date": "2024-06-18T15:04:45.998Z"
    },
    {
      "sl": 0,
      "tp": 0,
      "pips": 0,
      "pipValue": 0,
      "_id": "668bf9808259f96327d3f1b1",
      "externalId": "246190952",
      "accountId": "24186432",
      "closeDate": "2024-06-18T15:13:55.229Z",
      "comment": "",
      "createdAt": "2024-07-08T14:36:47.649Z",
      "entry": 2321.58,
      "exit": 2322.67,
      "fee": -0.4,
      "invalidReasons": [],
      "isClosed": true,
      "isPartial": false,
      "isValid": true,
      "openDate": "2024-06-18T15:04:45.754Z",
      "profitAndLoss": -11.3,
      "quantity": 0.1,
      "side": "Sell",
      "swap": 0,
      "symbol": "XAUUSD",
      "updatedAt": "2024-07-08T14:36:47.868Z",
      "id": "246190952",
      "date": "2024-06-18T15:04:45.754Z"
    },
    {
      "sl": 0,
      "tp": 0,
      "pips": 0,
      "pipValue": 0,
      "_id": "668bf9808259f96327d3ef93",
      "accountId": "24186432",
      "externalId": "246190949",
      "closeDate": "2024-06-18T15:13:55.229Z",
      "comment": "",
      "createdAt": "2024-07-08T14:36:47.623Z",
      "entry": 2321.58,
      "exit": 2322.67,
      "fee": -0.4,
      "invalidReasons": [],
      "isClosed": true,
      "isPartial": false,
      "isValid": true,
      "openDate": "2024-06-18T15:04:45.520Z",
      "profitAndLoss": -11.3,
      "quantity": 0.1,
      "side": "Sell",
      "swap": 0,
      "symbol": "XAUUSD",
      "updatedAt": "2024-07-08T14:36:47.869Z",
      "id": "246190949",
      "date": "2024-06-18T15:04:45.520Z"
    },
    {
      "sl": 0,
      "tp": 0,
      "pips": 0,
      "pipValue": 0,
      "_id": "668bf9808259f96327d3ef7b",
      "accountId": "24186432",
      "externalId": "246190928",
      "closeDate": "2024-06-18T15:13:42.852Z",
      "comment": "[sl 2322.39]",
      "createdAt": "2024-07-08T14:36:47.620Z",
      "entry": 2321.54,
      "exit": 2322.42,
      "fee": -0.4,
      "invalidReasons": [],
      "isClosed": true,
      "isPartial": false,
      "isValid": true,
      "openDate": "2024-06-18T15:04:44.437Z",
      "profitAndLoss": -9.200000000000001,
      "quantity": 0.1,
      "side": "Sell",
      "swap": 0,
      "symbol": "XAUUSD",
      "updatedAt": "2024-07-08T14:36:47.872Z",
      "id": "246190928",
      "date": "2024-06-18T15:04:44.437Z"
    },
    {
      "sl": 0,
      "tp": 0,
      "pips": 0,
      "pipValue": 0,
      "_id": "668bf9808259f96327d3ef8e",
      "externalId": "246190916",
      "accountId": "24186432",
      "closeDate": "2024-06-18T15:13:55.229Z",
      "comment": "",
      "createdAt": "2024-07-08T14:36:47.622Z",
      "entry": 2321.75,
      "exit": 2322.67,
      "fee": -0.4,
      "invalidReasons": [],
      "isClosed": true,
      "isPartial": false,
      "isValid": true,
      "openDate": "2024-06-18T15:04:43.074Z",
      "profitAndLoss": -9.6,
      "quantity": 0.1,
      "side": "Sell",
      "swap": 0,
      "symbol": "XAUUSD",
      "updatedAt": "2024-07-08T14:36:47.875Z",
      "id": "246190916",
      "date": "2024-06-18T15:04:43.074Z"
    },
    {
      "sl": 0,
      "tp": 0,
      "pips": 0,
      "pipValue": 0,
      "_id": "668bf9808259f96327d3ef2e",
      "accountId": "24186432",
      "externalId": "246189751",
      "closeDate": "2024-06-18T15:04:17.755Z",
      "comment": "[sl 2322.02]",
      "createdAt": "2024-07-08T14:36:47.589Z",
      "entry": 2323.21,
      "exit": 2322.02,
      "fee": -0.4,
      "invalidReasons": [],
      "isClosed": true,
      "isPartial": false,
      "isValid": true,
      "openDate": "2024-06-18T15:02:51.123Z",
      "profitAndLoss": -12.3,
      "quantity": 0.1,
      "side": "Buy",
      "swap": 0,
      "symbol": "XAUUSD",
      "updatedAt": "2024-07-08T14:36:47.874Z",
      "id": "246189751",
      "date": "2024-06-18T15:02:51.123Z"
    },
    {
      "sl": 0,
      "tp": 0,
      "pips": 0,
      "pipValue": 0,
      "_id": "668bf9808259f96327d3ef9c",
      "accountId": "24186432",
      "externalId": "246189553",
      "closeDate": "2024-06-18T15:04:16.647Z",
      "comment": "[sl 2322.14]",
      "createdAt": "2024-07-08T14:36:47.624Z",
      "entry": 2323.58,
      "exit": 2322.05,
      "fee": -0.4,
      "invalidReasons": [],
      "isClosed": true,
      "isPartial": false,
      "isValid": true,
      "openDate": "2024-06-18T15:02:13.292Z",
      "profitAndLoss": -15.700000000000001,
      "quantity": 0.1,
      "side": "Buy",
      "swap": 0,
      "symbol": "XAUUSD",
      "updatedAt": "2024-07-08T14:36:47.974Z",
      "id": "246189553",
      "date": "2024-06-18T15:02:13.292Z"
    },
    {
      "sl": 0,
      "tp": 0,
      "pips": 0,
      "pipValue": 0,
      "_id": "668bf9808259f96327d3ef23",
      "accountId": "24186432",
      "externalId": "246188324",
      "closeDate": "2024-06-18T15:04:17.754Z",
      "comment": "[sl 2322.02]",
      "createdAt": "2024-07-08T14:36:47.588Z",
      "entry": 2323.69,
      "exit": 2322.02,
      "fee": -0.4,
      "invalidReasons": [],
      "isClosed": true,
      "isPartial": false,
      "isValid": true,
      "openDate": "2024-06-18T14:59:49.762Z",
      "profitAndLoss": -17.099999999999998,
      "quantity": 0.1,
      "side": "Buy",
      "swap": 0,
      "symbol": "XAUUSD",
      "updatedAt": "2024-07-08T14:36:47.873Z",
      "id": "246188324",
      "date": "2024-06-18T14:59:49.762Z"
    },
    {
      "sl": 0,
      "tp": 0,
      "pips": 0,
      "pipValue": 0,
      "_id": "668bf9808259f96327d3ef2a",
      "accountId": "24186432",
      "externalId": "246188268",
      "closeDate": "2024-06-18T15:04:16.647Z",
      "comment": "[sl 2322.06]",
      "createdAt": "2024-07-08T14:36:47.589Z",
      "entry": 2323.39,
      "exit": 2322.05,
      "fee": -0.4,
      "invalidReasons": [],
      "isClosed": true,
      "isPartial": false,
      "isValid": true,
      "openDate": "2024-06-18T14:59:39.119Z",
      "profitAndLoss": -13.8,
      "quantity": 0.1,
      "side": "Buy",
      "swap": 0,
      "symbol": "XAUUSD",
      "updatedAt": "2024-07-08T14:36:47.915Z",
      "id": "246188268",
      "date": "2024-06-18T14:59:39.119Z"
    },
    {
      "sl": 0,
      "tp": 0,
      "pips": 0,
      "pipValue": 0,
      "_id": "668bf9808259f96327d3f455",
      "accountId": "24186432",
      "externalId": "246186497",
      "closeDate": "2024-06-18T15:04:16.647Z",
      "comment": "[sl 2322.07]",
      "createdAt": "2024-07-08T14:36:47.639Z",
      "entry": 2324.53,
      "exit": 2322.05,
      "fee": -0.4,
      "invalidReasons": [],
      "isClosed": true,
      "isPartial": false,
      "isValid": true,
      "openDate": "2024-06-18T14:55:05.878Z",
      "profitAndLoss": -25.2,
      "quantity": 0.1,
      "side": "Buy",
      "swap": 0,
      "symbol": "XAUUSD",
      "updatedAt": "2024-07-08T14:36:47.876Z",
      "id": "246186497",
      "date": "2024-06-18T14:55:05.878Z"
    },
    {
      "sl": 0,
      "tp": 0,
      "pips": 0,
      "pipValue": 0,
      "_id": "668bf97f8259f96327d3eecc",
      "accountId": "24186432",
      "externalId": "246186106",
      "closeDate": "2024-06-18T15:04:18.059Z",
      "comment": "[sl 2322.00]",
      "createdAt": "2024-07-08T14:36:47.623Z",
      "entry": 2324.77,
      "exit": 2321.96,
      "fee": -0.4,
      "invalidReasons": [],
      "isClosed": true,
      "isPartial": false,
      "isValid": true,
      "openDate": "2024-06-18T14:54:24.380Z",
      "profitAndLoss": -28.5,
      "quantity": 0.1,
      "side": "Buy",
      "swap": 0,
      "symbol": "XAUUSD",
      "updatedAt": "2024-07-08T14:36:47.876Z",
      "id": "246186106",
      "date": "2024-06-18T14:54:24.380Z"
    },
    {
      "sl": 0,
      "tp": 0,
      "pips": 0,
      "pipValue": 0,
      "_id": "668bf9808259f96327d3f01a",
      "accountId": "24186432",
      "externalId": "246184738",
      "closeDate": "2024-06-18T15:04:18.058Z",
      "comment": "[sl 2322.00]",
      "createdAt": "2024-07-08T14:36:47.654Z",
      "entry": 2325.35,
      "exit": 2321.96,
      "fee": -0.4,
      "invalidReasons": [],
      "isClosed": true,
      "isPartial": false,
      "isValid": true,
      "openDate": "2024-06-18T14:52:05.039Z",
      "profitAndLoss": -34.3,
      "quantity": 0.1,
      "side": "Buy",
      "swap": 0,
      "symbol": "XAUUSD",
      "updatedAt": "2024-07-08T14:36:47.871Z",
      "id": "246184738",
      "date": "2024-06-18T14:52:05.039Z"
    },
    {
      "sl": 0,
      "tp": 0,
      "pips": 0,
      "pipValue": 0,
      "_id": "668bf97f8259f96327d3edf6",
      "externalId": "246184728",
      "accountId": "24186432",
      "closeDate": "2024-06-18T15:04:18.058Z",
      "comment": "[sl 2322.00]",
      "createdAt": "2024-07-08T14:36:47.607Z",
      "entry": 2325.35,
      "exit": 2321.96,
      "fee": -0.4,
      "invalidReasons": [],
      "isClosed": true,
      "isPartial": false,
      "isValid": true,
      "openDate": "2024-06-18T14:52:03.856Z",
      "profitAndLoss": -34.3,
      "quantity": 0.1,
      "side": "Buy",
      "swap": 0,
      "symbol": "XAUUSD",
      "updatedAt": "2024-07-08T14:36:47.870Z",
      "id": "246184728",
      "date": "2024-06-18T14:52:03.856Z"
    },
    {
      "sl": 0,
      "tp": 0,
      "pips": 0,
      "pipValue": 0,
      "_id": "668bf97f8259f96327d3ef04",
      "accountId": "24186432",
      "externalId": "246183469",
      "closeDate": "2024-06-18T15:04:16.646Z",
      "comment": "[sl 2322.05]",
      "createdAt": "2024-07-08T14:36:47.619Z",
      "entry": 2324.87,
      "exit": 2322.05,
      "fee": -0.4,
      "invalidReasons": [],
      "isClosed": true,
      "isPartial": false,
      "isValid": true,
      "openDate": "2024-06-18T14:50:36.447Z",
      "profitAndLoss": -28.599999999999998,
      "quantity": 0.1,
      "side": "Buy",
      "swap": 0,
      "symbol": "XAUUSD",
      "updatedAt": "2024-07-08T14:36:47.873Z",
      "id": "246183469",
      "date": "2024-06-18T14:50:36.447Z"
    },
    {
      "sl": 0,
      "tp": 0,
      "pips": 0,
      "pipValue": 0,
      "_id": "668bf97f8259f96327d3ed78",
      "accountId": "24186432",
      "externalId": "246183410",
      "closeDate": "2024-06-18T15:04:18.058Z",
      "comment": "[sl 2322.00]",
      "createdAt": "2024-07-08T14:36:47.595Z",
      "entry": 2324.83,
      "exit": 2321.96,
      "fee": -0.4,
      "invalidReasons": [],
      "isClosed": true,
      "isPartial": false,
      "isValid": true,
      "openDate": "2024-06-18T14:50:31.896Z",
      "profitAndLoss": -29.099999999999998,
      "quantity": 0.1,
      "side": "Buy",
      "swap": 0,
      "symbol": "XAUUSD",
      "updatedAt": "2024-07-08T14:36:47.884Z",
      "id": "246183410",
      "date": "2024-06-18T14:50:31.896Z"
    },
    {
      "sl": 0,
      "tp": 0,
      "pips": 0,
      "pipValue": 0,
      "_id": "668bf97f8259f96327d3eec3",
      "accountId": "24186432",
      "externalId": "246183387",
      "closeDate": "2024-06-18T15:04:16.645Z",
      "comment": "[sl 2322.05]",
      "createdAt": "2024-07-08T14:36:47.621Z",
      "entry": 2324.71,
      "exit": 2322.05,
      "fee": -0.4,
      "invalidReasons": [],
      "isClosed": true,
      "isPartial": false,
      "isValid": true,
      "openDate": "2024-06-18T14:50:30.656Z",
      "profitAndLoss": -27,
      "quantity": 0.1,
      "side": "Buy",
      "swap": 0,
      "symbol": "XAUUSD",
      "updatedAt": "2024-07-08T14:36:47.925Z",
      "id": "246183387",
      "date": "2024-06-18T14:50:30.656Z"
    },
    {
      "sl": 0,
      "tp": 0,
      "pips": 0,
      "pipValue": 0,
      "_id": "668bf97f8259f96327d3ecf3",
      "accountId": "24186432",
      "externalId": "246182848",
      "closeDate": "2024-06-18T15:04:18.058Z",
      "comment": "[sl 2322.00]",
      "createdAt": "2024-07-08T14:36:47.554Z",
      "entry": 2324.02,
      "exit": 2321.96,
      "fee": -0.4,
      "invalidReasons": [],
      "isClosed": true,
      "isPartial": false,
      "isValid": true,
      "openDate": "2024-06-18T14:49:52.351Z",
      "profitAndLoss": -21,
      "quantity": 0.1,
      "side": "Buy",
      "swap": 0,
      "symbol": "XAUUSD",
      "updatedAt": "2024-07-08T14:36:47.835Z",
      "id": "246182848",
      "date": "2024-06-18T14:49:52.351Z"
    },
    {
      "sl": 0,
      "tp": 0,
      "pips": 0,
      "pipValue": 0,
      "_id": "668bf97f8259f96327d3eca3",
      "accountId": "24186432",
      "externalId": "246182838",
      "closeDate": "2024-06-18T15:04:16.643Z",
      "comment": "[sl 2322.10]",
      "createdAt": "2024-07-08T14:36:47.537Z",
      "entry": 2324.03,
      "exit": 2322.05,
      "fee": -0.4,
      "invalidReasons": [],
      "isClosed": true,
      "isPartial": false,
      "isValid": true,
      "openDate": "2024-06-18T14:49:50.823Z",
      "profitAndLoss": -20.2,
      "quantity": 0.1,
      "side": "Buy",
      "swap": 0,
      "symbol": "XAUUSD",
      "updatedAt": "2024-07-08T14:36:47.750Z",
      "id": "246182838",
      "date": "2024-06-18T14:49:50.823Z"
    },
    {
      "sl": 0,
      "tp": 0,
      "pips": 0,
      "pipValue": 0,
      "_id": "668bf97f8259f96327d3eea7",
      "accountId": "24186432",
      "externalId": "246182793",
      "closeDate": "2024-06-18T15:04:18.057Z",
      "comment": "[sl 2322.00]",
      "createdAt": "2024-07-08T14:36:47.622Z",
      "entry": 2324.02,
      "exit": 2321.96,
      "fee": -0.4,
      "invalidReasons": [],
      "isClosed": true,
      "isPartial": false,
      "isValid": true,
      "openDate": "2024-06-18T14:49:46.196Z",
      "profitAndLoss": -21,
      "quantity": 0.1,
      "side": "Buy",
      "swap": 0,
      "symbol": "XAUUSD",
      "updatedAt": "2024-07-08T14:36:47.769Z",
      "id": "246182793",
      "date": "2024-06-18T14:49:46.196Z"
    },
    {
      "sl": 0,
      "tp": 0,
      "pips": 0,
      "pipValue": 0,
      "_id": "668bf97f8259f96327d3ebf5",
      "externalId": "246182777",
      "accountId": "24186432",
      "closeDate": "2024-06-18T15:04:18.056Z",
      "comment": "[sl 2322.00]",
      "createdAt": "2024-07-08T14:36:47.548Z",
      "entry": 2324.01,
      "exit": 2321.96,
      "fee": -0.4,
      "invalidReasons": [],
      "isClosed": true,
      "isPartial": false,
      "isValid": true,
      "openDate": "2024-06-18T14:49:44.595Z",
      "profitAndLoss": -20.9,
      "quantity": 0.1,
      "side": "Buy",
      "swap": 0,
      "symbol": "XAUUSD",
      "updatedAt": "2024-07-08T14:36:47.746Z",
      "id": "246182777",
      "date": "2024-06-18T14:49:44.595Z"
    }
  ]
}