{
  "highStakesWithdrawalCount": 0,
  "_id": "686b9dd228ef468abd52ab12",
  "userId": "c7e984df-d505-4af2-95cf-148d0bc64880",
  "orderId": "3193686",
  "programId": "67306d0318bda20ad718add6",
  "tsAccount": "25439044",
  "tsAccountId": "25439044",
  "tradingSystem": "meta-trader-5",
  "status": "disabled",
  "type": "evaluation",
  "state": {
    "terminated": false,
    "dailyPause": false,
    "dailyLoss": false,
    "target": true,
    "expired": false
  },
  "boosters": [],
  "level": 1,
  "creationRetries": 0,
  "createdAt": "2025-07-07T10:13:38.117Z",
  "updatedAt": "2025-07-11T23:51:03.104Z",
  "config": {
    "hasSeen": true
  },
  "purchaseId": "3193686",
  "assetClass": "forex",
  "accountId": "25439044",
  "name": "EVALUATION 25439044",
  "balance": 10808.5,
  "equity": 10808.5,
  "pnl": 838.7700000000007,
  "stats": {
    "totalFees": 0,
    "totalRebatedFees": 0,
    "_id": "686b9de6069059d2f03ac2e4",
    "accountId": "25439044",
    "avgLoss": -49.80966666666666,
    "avgProfit": 111.09809523809525,
    "avgTradeDuration": 14529145.823529411,
    "avgTradeSize": 0.17156862745098045,
    "bestProfit": 622.8,
    "biggestLoss": -161,
    "createdAt": "2025-07-07T10:13:58.817Z",
    "expectancy": 16.4464705882353,
    "grossLoss": -1494.2899999999997,
    "grossProfit": 2333.0600000000004,
    "longTrades": 25,
    "lossTrades": 30,
    "profitFactor": 1.5613167457454717,
    "profitTrades": 21,
    "shortTrades": 26,
    "totalNetProfit": 838.7700000000007,
    "totalPositionDuration": 740986437,
    "totalQuantity": 8.750000000000004,
    "totalTrades": 51,
    "updatedAt": "2025-07-11T23:49:31.371Z",
    "winRate": 0.4117647058823529,
    "latestPositionDate": "2025-07-07T10:16:31.124Z"
  },
  "balanceDetails": {
    "unrealized": 0,
    "balance": 10808.5,
    "baseBalance": 10000,
    "credits": 0,
    "profitCredits": 0,
    "refundCredits": 0,
    "equity": 10808.5,
    "maxLoss": 1000,
    "profitAndLoss": 838.77,
    "dailyProfitAndLoss": 0,
    "weeklyProfitAndLoss": 0,
    "invalidProfitAndLoss": 0,
    "snapshotEquity": 10808.5,
    "snapshotBalance": 10808.5,
    "allowedDailyLosses": -540.4250000000001,
    "syncDate": "2025-07-11T23:49:31.259Z",
    "consecutiveInactivityDays": 0,
    "highWaterMark": 0,
    "growthPercentage": 8.387699999999999,
    "highWaterMarkPnl": 10838.77
  },
  "trades": [
    {
      "_id": "6870d272069059d2f0ab4095",
      "accountId": "25439044",
      "externalId": "402236925",
      "closeDate": "2025-07-11T11:15:16.982Z",
      "comment": "",
      "createdAt": "2025-07-11T08:59:30.931Z",
      "entry": 3333.55,
      "exit": 3348.26,
      "fee": -0.8,
      "invalidReasons": [],
      "isClosed": true,
      "isPartial": false,
      "isValid": true,
      "openDate": "2025-07-11T08:59:05.147Z",
      "pipValue": -1.9945615227736233,
      "pips": -147.1,
      "profitAndLoss": 293.4,
      "quantity": 0.2,
      "side": "Buy",
      "sl": 3339.07,
      "swap": 0,
      "symbol": "XAUUSD",
      "tp": 3349.06,
      "updatedAt": "2025-07-11T23:49:31.309Z",
      "id": "402236925",
      "date": "2025-07-11T08:59:05.147Z"
    },
    {
      "_id": "6870d1dc069059d2f0aadffd",
      "accountId": "25439044",
      "externalId": "402236028",
      "closeDate": "2025-07-11T11:15:16.981Z",
      "comment": "",
      "createdAt": "2025-07-11T08:57:00.692Z",
      "entry": 3334.89,
      "exit": 3348.26,
      "fee": -1.2,
      "invalidReasons": [],
      "isClosed": true,
      "isPartial": false,
      "isValid": true,
      "openDate": "2025-07-11T08:56:43.660Z",
      "pipValue": -2.9910246821241593,
      "pips": -133.7,
      "profitAndLoss": 399.9,
      "quantity": 0.3,
      "side": "Buy",
      "sl": 3339.11,
      "swap": 0,
      "symbol": "XAUUSD",
      "tp": 3349.06,
      "updatedAt": "2025-07-11T23:49:31.308Z",
      "id": "402236028",
      "date": "2025-07-11T08:56:43.660Z"
    },
    {
      "_id": "6870d1dc069059d2f0aae220",
      "accountId": "25439044",
      "externalId": "402235960",
      "closeDate": "2025-07-11T11:15:16.981Z",
      "comment": "",
      "createdAt": "2025-07-11T08:57:00.792Z",
      "entry": 3335.7,
      "exit": 3348.26,
      "fee": -1.2,
      "invalidReasons": [],
      "isClosed": true,
      "isPartial": false,
      "isValid": true,
      "openDate": "2025-07-11T08:56:35.839Z",
      "pipValue": -2.9904458598726116,
      "pips": -125.6,
      "profitAndLoss": 375.6,
      "quantity": 0.3,
      "side": "Buy",
      "sl": 3339.2,
      "swap": 0,
      "symbol": "XAUUSD",
      "tp": 3348.99,
      "updatedAt": "2025-07-11T23:49:31.362Z",
      "id": "402235960",
      "date": "2025-07-11T08:56:35.839Z"
    },
    {
      "_id": "6870b95e069059d2f096630a",
      "accountId": "25439044",
      "externalId": "402176358",
      "closeDate": "2025-07-11T08:53:53.093Z",
      "comment": "[sl 3333.87]",
      "createdAt": "2025-07-11T07:12:30.683Z",
      "entry": 3333.43,
      "exit": 3333.59,
      "fee": -1.2,
      "invalidReasons": [],
      "isClosed": true,
      "isPartial": false,
      "isValid": true,
      "openDate": "2025-07-11T07:12:25.365Z",
      "pipValue": -2.2499999999999996,
      "pips": -1.6,
      "profitAndLoss": 3.6,
      "quantity": 0.3,
      "side": "Buy",
      "sl": 3333.87,
      "swap": 0,
      "symbol": "XAUUSD",
      "tp": 3347.31,
      "updatedAt": "2025-07-11T23:49:31.351Z",
      "id": "402176358",
      "date": "2025-07-11T07:12:25.365Z"
    },
    {
      "_id": "6870b6ca069059d2f0942a27",
      "accountId": "25439044",
      "externalId": "402168859",
      "closeDate": "2025-07-11T08:53:53.088Z",
      "comment": "[sl 3333.87]",
      "createdAt": "2025-07-11T07:01:30.936Z",
      "entry": 3333.17,
      "exit": 3333.59,
      "fee": -2,
      "invalidReasons": [],
      "isClosed": true,
      "isPartial": false,
      "isValid": true,
      "openDate": "2025-07-11T07:01:12.365Z",
      "pipValue": -4.523809523809524,
      "pips": -4.2,
      "profitAndLoss": 19,
      "quantity": 0.5,
      "side": "Buy",
      "sl": 3333.87,
      "swap": 0,
      "symbol": "XAUUSD",
      "tp": 3347.27,
      "updatedAt": "2025-07-11T23:49:31.362Z",
      "id": "402168859",
      "date": "2025-07-11T07:01:12.365Z"
    },
    {
      "_id": "68709852069059d2f07ea1c6",
      "externalId": "402109085",
      "accountId": "25439044",
      "closeDate": "2025-07-11T07:00:09.572Z",
      "comment": "[sl 3331.97]",
      "createdAt": "2025-07-11T04:51:30.569Z",
      "entry": 3331.57,
      "exit": 3331.89,
      "fee": -2,
      "invalidReasons": [],
      "isClosed": true,
      "isPartial": false,
      "isValid": true,
      "openDate": "2025-07-11T04:51:20.732Z",
      "pipValue": -4.375,
      "pips": -3.2,
      "profitAndLoss": 14,
      "quantity": 0.5,
      "side": "Buy",
      "sl": 3331.97,
      "swap": 0,
      "symbol": "XAUUSD",
      "tp": 3353.63,
      "updatedAt": "2025-07-11T23:49:31.357Z",
      "id": "402109085",
      "date": "2025-07-11T04:51:20.732Z"
    },
    {
      "_id": "687071c4069059d2f06fb727",
      "accountId": "25439044",
      "externalId": "402072744",
      "closeDate": "2025-07-11T04:34:29.225Z",
      "comment": "",
      "createdAt": "2025-07-11T02:07:00.766Z",
      "entry": 3329.16,
      "exit": 3331.13,
      "fee": -2,
      "invalidReasons": [],
      "isClosed": true,
      "isPartial": false,
      "isValid": true,
      "openDate": "2025-07-11T02:06:40.188Z",
      "pipValue": -4.898477157360406,
      "pips": -19.7,
      "profitAndLoss": 96.5,
      "quantity": 0.5,
      "side": "Buy",
      "sl": 3330.47,
      "swap": 0,
      "symbol": "XAUUSD",
      "tp": 3353.32,
      "updatedAt": "2025-07-11T23:49:31.360Z",
      "id": "402072744",
      "date": "2025-07-11T02:06:40.188Z"
    },
    {
      "_id": "68706a26069059d2f06c2292",
      "accountId": "25439044",
      "externalId": "402064532",
      "closeDate": "2025-07-11T01:51:36.886Z",
      "comment": "",
      "createdAt": "2025-07-11T01:34:30.765Z",
      "entry": 3330.02,
      "exit": 3329.05,
      "fee": -2,
      "invalidReasons": [],
      "isClosed": true,
      "isPartial": false,
      "isValid": true,
      "openDate": "2025-07-11T01:34:07.074Z",
      "pipValue": -5.206185567010309,
      "pips": 9.7,
      "profitAndLoss": -50.5,
      "quantity": 0.5,
      "side": "Buy",
      "sl": 3324.95,
      "swap": 0,
      "symbol": "XAUUSD",
      "tp": 3354.54,
      "updatedAt": "2025-07-11T23:49:31.352Z",
      "id": "402064532",
      "date": "2025-07-11T01:34:07.074Z"
    },
    {
      "_id": "68706666069059d2f06a617e",
      "externalId": "402059711",
      "accountId": "25439044",
      "closeDate": "2025-07-11T01:33:43.495Z",
      "comment": "",
      "createdAt": "2025-07-11T01:18:30.748Z",
      "entry": 3325.56,
      "exit": 3330.04,
      "fee": -0.12,
      "invalidReasons": [],
      "isClosed": true,
      "isPartial": false,
      "isValid": true,
      "openDate": "2025-07-11T01:18:11.787Z",
      "pipValue": -0.3026785714285714,
      "pips": 44.8,
      "profitAndLoss": -13.56,
      "quantity": 0.03,
      "side": "Sell",
      "sl": 0,
      "swap": 0,
      "symbol": "XAUUSD",
      "tp": 0,
      "updatedAt": "2025-07-11T23:49:31.361Z",
      "id": "402059711",
      "date": "2025-07-11T01:18:11.787Z"
    },
    {
      "_id": "686fc364069059d2f00dd68b",
      "externalId": "401814602",
      "accountId": "25439044",
      "closeDate": "2025-07-10T18:49:07.028Z",
      "comment": "[sl 3319.77]",
      "createdAt": "2025-07-10T13:43:00.780Z",
      "entry": 3323.87,
      "exit": 3319.89,
      "fee": -0.12,
      "invalidReasons": [],
      "isClosed": true,
      "isPartial": false,
      "isValid": true,
      "openDate": "2025-07-10T13:42:35.247Z",
      "pipValue": -0.2969849246231156,
      "pips": -39.8,
      "profitAndLoss": 11.82,
      "quantity": 0.03,
      "side": "Sell",
      "sl": 3319.77,
      "swap": 0,
      "symbol": "XAUUSD",
      "tp": 0,
      "updatedAt": "2025-07-11T23:49:31.356Z",
      "id": "401814602",
      "date": "2025-07-10T13:42:35.247Z"
    },
    {
      "_id": "686fbb6c069059d2f0030d34",
      "accountId": "25439044",
      "externalId": "401781747",
      "closeDate": "2025-07-10T18:49:12.107Z",
      "comment": "[sl 3320.06]",
      "createdAt": "2025-07-10T13:09:00.741Z",
      "entry": 3325.26,
      "exit": 3320.07,
      "fee": -0.12,
      "invalidReasons": [],
      "isClosed": true,
      "isPartial": false,
      "isValid": true,
      "openDate": "2025-07-10T13:08:45.289Z",
      "pipValue": -0.29768786127167635,
      "pips": -51.9,
      "profitAndLoss": 15.45,
      "quantity": 0.03,
      "side": "Sell",
      "sl": 3320.06,
      "swap": 0,
      "symbol": "XAUUSD",
      "tp": 0,
      "updatedAt": "2025-07-11T23:49:31.359Z",
      "id": "401781747",
      "date": "2025-07-10T13:08:45.289Z"
    },
    {
      "_id": "686f6767069059d2f0bcd3ab",
      "accountId": "25439044",
      "externalId": "401589688",
      "closeDate": "2025-07-10T18:49:07.076Z",
      "comment": "[sl 3319.90]",
      "createdAt": "2025-07-10T07:10:31.031Z",
      "entry": 3328.44,
      "exit": 3319.9,
      "fee": -0.6,
      "invalidReasons": [],
      "isClosed": true,
      "isPartial": false,
      "isValid": true,
      "openDate": "2025-07-10T07:10:02.338Z",
      "pipValue": -1.4929742388758782,
      "pips": -85.4,
      "profitAndLoss": 127.5,
      "quantity": 0.15,
      "side": "Sell",
      "sl": 3319.9,
      "swap": 0,
      "symbol": "XAUUSD",
      "tp": 0,
      "updatedAt": "2025-07-11T23:49:31.353Z",
      "id": "401589688",
      "date": "2025-07-10T07:10:02.338Z"
    },
    {
      "_id": "686f654b069059d2f0ba97eb",
      "accountId": "25439044",
      "externalId": "401583183",
      "closeDate": "2025-07-10T18:47:50.207Z",
      "comment": "[sl 3319.51]",
      "createdAt": "2025-07-10T07:01:30.993Z",
      "entry": 3326.33,
      "exit": 3319.55,
      "fee": -0.6,
      "invalidReasons": [],
      "isClosed": true,
      "isPartial": false,
      "isValid": true,
      "openDate": "2025-07-10T07:01:19.184Z",
      "pipValue": -1.4911504424778763,
      "pips": -67.8,
      "profitAndLoss": 101.1,
      "quantity": 0.15,
      "side": "Sell",
      "sl": 3319.51,
      "swap": 0,
      "symbol": "XAUUSD",
      "tp": 0,
      "updatedAt": "2025-07-11T23:49:31.364Z",
      "id": "401583183",
      "date": "2025-07-10T07:01:19.184Z"
    },
    {
      "_id": "686f5c63069059d2f0b4ad95",
      "accountId": "25439044",
      "externalId": "401559815",
      "closeDate": "2025-07-10T07:09:43.326Z",
      "comment": "",
      "createdAt": "2025-07-10T06:23:31.124Z",
      "entry": 3324.09,
      "exit": 3329.22,
      "fee": -0.6,
      "invalidReasons": [],
      "isClosed": true,
      "isPartial": false,
      "isValid": true,
      "openDate": "2025-07-10T06:23:15.405Z",
      "pipValue": -1.5116959064327486,
      "pips": 51.3,
      "profitAndLoss": -77.55,
      "quantity": 0.15,
      "side": "Sell",
      "sl": 0,
      "swap": 0,
      "symbol": "XAUUSD",
      "tp": 0,
      "updatedAt": "2025-07-11T23:49:31.363Z",
      "id": "401559815",
      "date": "2025-07-10T06:23:15.405Z"
    },
    {
      "_id": "686f580c069059d2f0b0e55c",
      "externalId": "401555219",
      "accountId": "25439044",
      "closeDate": "2025-07-10T18:49:07.027Z",
      "comment": "[sl 3319.75]",
      "createdAt": "2025-07-10T06:05:00.739Z",
      "entry": 3321.6,
      "exit": 3319.89,
      "fee": -0.12,
      "invalidReasons": [],
      "isClosed": true,
      "isPartial": false,
      "isValid": true,
      "openDate": "2025-07-10T06:05:00.252Z",
      "pipValue": -0.29298245614035084,
      "pips": -17.1,
      "profitAndLoss": 5.01,
      "quantity": 0.03,
      "side": "Sell",
      "sl": 3319.75,
      "swap": 0,
      "symbol": "XAUUSD",
      "tp": 0,
      "updatedAt": "2025-07-11T23:49:31.380Z",
      "id": "401555219",
      "date": "2025-07-10T06:05:00.252Z"
    },
    {
      "_id": "686f4a92069059d2f0a9a394",
      "accountId": "25439044",
      "externalId": "401537886",
      "closeDate": "2025-07-10T18:49:07.026Z",
      "comment": "[sl 3319.80]",
      "createdAt": "2025-07-10T05:07:30.555Z",
      "entry": 3322.87,
      "exit": 3319.89,
      "fee": -0.12,
      "invalidReasons": [],
      "isClosed": true,
      "isPartial": false,
      "isValid": true,
      "openDate": "2025-07-10T05:07:20.682Z",
      "pipValue": -0.2959731543624161,
      "pips": -29.8,
      "profitAndLoss": 8.82,
      "quantity": 0.03,
      "side": "Sell",
      "sl": 3319.8,
      "swap": 0,
      "symbol": "XAUUSD",
      "tp": 0,
      "updatedAt": "2025-07-11T23:49:31.379Z",
      "id": "401537886",
      "date": "2025-07-10T05:07:20.682Z"
    },
    {
      "_id": "686f391c069059d2f0a19f6c",
      "accountId": "25439044",
      "externalId": "401515988",
      "closeDate": "2025-07-10T13:00:19.464Z",
      "comment": "[sl 3328.37]",
      "createdAt": "2025-07-10T03:53:00.526Z",
      "entry": 3317.8,
      "exit": 3328.12,
      "fee": -0.12,
      "invalidReasons": [],
      "isClosed": true,
      "isPartial": false,
      "isValid": true,
      "openDate": "2025-07-10T03:52:48.962Z",
      "pipValue": -0.30116279069767443,
      "pips": 103.2,
      "profitAndLoss": -31.08,
      "quantity": 0.03,
      "side": "Sell",
      "sl": 3328.37,
      "swap": 0,
      "symbol": "XAUUSD",
      "tp": 3247.82,
      "updatedAt": "2025-07-11T23:49:31.367Z",
      "id": "401515988",
      "date": "2025-07-10T03:52:48.962Z"
    },
    {
      "_id": "686f292c069059d2f09b8c85",
      "accountId": "25439044",
      "externalId": "401501127",
      "closeDate": "2025-07-10T13:00:32.631Z",
      "comment": "[sl 3329.36]",
      "createdAt": "2025-07-10T02:45:00.998Z",
      "entry": 3319.33,
      "exit": 3329.38,
      "fee": -0.12,
      "invalidReasons": [],
      "isClosed": true,
      "isPartial": false,
      "isValid": true,
      "openDate": "2025-07-10T02:44:44.177Z",
      "pipValue": -0.3011940298507463,
      "pips": 100.5,
      "profitAndLoss": -30.27,
      "quantity": 0.03,
      "side": "Sell",
      "sl": 3329.36,
      "swap": 0,
      "symbol": "XAUUSD",
      "tp": 0,
      "updatedAt": "2025-07-11T23:49:31.394Z",
      "id": "401501127",
      "date": "2025-07-10T02:44:44.177Z"
    },
    {
      "_id": "686f2800069059d2f09b06d8",
      "accountId": "25439044",
      "externalId": "401499535",
      "closeDate": "2025-07-10T18:49:07.025Z",
      "comment": "[sl 3319.78]",
      "createdAt": "2025-07-10T02:40:00.831Z",
      "entry": 3321.36,
      "exit": 3319.88,
      "fee": -0.12,
      "invalidReasons": [],
      "isClosed": true,
      "isPartial": false,
      "isValid": true,
      "openDate": "2025-07-10T02:39:47.828Z",
      "pipValue": -0.2918918918918919,
      "pips": -14.8,
      "profitAndLoss": 4.32,
      "quantity": 0.03,
      "side": "Sell",
      "sl": 3319.78,
      "swap": 0,
      "symbol": "XAUUSD",
      "tp": 3247.98,
      "updatedAt": "2025-07-11T23:49:31.365Z",
      "id": "401499535",
      "date": "2025-07-10T02:39:47.828Z"
    },
    {
      "_id": "686f18e2069059d2f0941e64",
      "accountId": "25439044",
      "externalId": "401485565",
      "closeDate": "2025-07-10T18:47:50.204Z",
      "comment": "[sl 3319.49]",
      "createdAt": "2025-07-10T01:35:30.881Z",
      "entry": 3323.98,
      "exit": 3319.55,
      "fee": -0.12,
      "invalidReasons": [],
      "isClosed": true,
      "isPartial": false,
      "isValid": true,
      "openDate": "2025-07-10T01:35:08.589Z",
      "pipValue": -0.29729119638826185,
      "pips": -44.3,
      "profitAndLoss": 13.17,
      "quantity": 0.03,
      "side": "Sell",
      "sl": 3319.49,
      "swap": 0,
      "symbol": "XAUUSD",
      "tp": 0,
      "updatedAt": "2025-07-11T23:49:31.391Z",
      "id": "401485565",
      "date": "2025-07-10T01:35:08.589Z"
    },
    {
      "_id": "686f13ba069059d2f091a0e2",
      "accountId": "25439044",
      "externalId": "401478696",
      "closeDate": "2025-07-10T18:49:07.024Z",
      "comment": "[sl 3319.82]",
      "createdAt": "2025-07-10T01:13:30.904Z",
      "entry": 3322.13,
      "exit": 3319.88,
      "fee": -0.12,
      "invalidReasons": [],
      "isClosed": true,
      "isPartial": false,
      "isValid": true,
      "openDate": "2025-07-10T01:13:17.796Z",
      "pipValue": -0.2946666666666667,
      "pips": -22.5,
      "profitAndLoss": 6.63,
      "quantity": 0.03,
      "side": "Sell",
      "sl": 3319.82,
      "swap": 0,
      "symbol": "XAUUSD",
      "tp": 3247.47,
      "updatedAt": "2025-07-11T23:49:31.385Z",
      "id": "401478696",
      "date": "2025-07-10T01:13:17.796Z"
    },
    {
      "_id": "686f0f0a069059d2f08f5425",
      "accountId": "25439044",
      "externalId": "401472427",
      "closeDate": "2025-07-10T06:10:33.716Z",
      "comment": "",
      "createdAt": "2025-07-10T00:53:30.551Z",
      "entry": 3318.57,
      "exit": 3323.96,
      "fee": -0.2,
      "invalidReasons": [],
      "isClosed": true,
      "isPartial": false,
      "isValid": true,
      "openDate": "2025-07-10T00:53:21.703Z",
      "pipValue": -0.5037105751391465,
      "pips": 53.9,
      "profitAndLoss": -27.15,
      "quantity": 0.05,
      "side": "Sell",
      "sl": 0,
      "swap": 0,
      "symbol": "XAUUSD",
      "tp": 3247.64,
      "updatedAt": "2025-07-11T23:49:31.380Z",
      "id": "401472427",
      "date": "2025-07-10T00:53:21.703Z"
    },
    {
      "_id": "686f0d48069059d2f08ec15d",
      "accountId": "25439044",
      "externalId": "401470922",
      "closeDate": "2025-07-10T18:49:06.973Z",
      "comment": "[sl 3319.70]",
      "createdAt": "2025-07-10T00:46:00.792Z",
      "entry": 3320.13,
      "exit": 3319.71,
      "fee": -0.12,
      "invalidReasons": [],
      "isClosed": true,
      "isPartial": false,
      "isValid": true,
      "openDate": "2025-07-10T00:45:40.137Z",
      "pipValue": -0.27142857142857146,
      "pips": -4.2,
      "profitAndLoss": 1.14,
      "quantity": 0.03,
      "side": "Sell",
      "sl": 3319.7,
      "swap": 0,
      "symbol": "XAUUSD",
      "tp": 3247.55,
      "updatedAt": "2025-07-11T23:49:31.391Z",
      "id": "401470922",
      "date": "2025-07-10T00:45:40.137Z"
    },
    {
      "_id": "686dfe76069059d2f0d2dd67",
      "accountId": "25439044",
      "externalId": "400985325",
      "closeDate": "2025-07-09T07:20:22.644Z",
      "comment": "",
      "createdAt": "2025-07-09T05:30:30.831Z",
      "entry": 3291.35,
      "exit": 3294.04,
      "fee": -0.4,
      "invalidReasons": [],
      "isClosed": true,
      "isPartial": false,
      "isValid": true,
      "openDate": "2025-07-09T05:30:15.941Z",
      "pipValue": -1.0148698884758365,
      "pips": 26.9,
      "profitAndLoss": -27.3,
      "quantity": 0.1,
      "side": "Sell",
      "sl": 3294.75,
      "swap": 0,
      "symbol": "XAUUSD",
      "tp": 3246.29,
      "updatedAt": "2025-07-11T23:49:31.383Z",
      "id": "400985325",
      "date": "2025-07-09T05:30:15.941Z"
    },
    {
      "_id": "686dfde0069059d2f0d288b9",
      "accountId": "25439044",
      "externalId": "400984226",
      "closeDate": "2025-07-09T07:20:22.633Z",
      "comment": "",
      "createdAt": "2025-07-09T05:28:00.814Z",
      "entry": 3292.24,
      "exit": 3294.04,
      "fee": -0.4,
      "invalidReasons": [],
      "isClosed": true,
      "isPartial": false,
      "isValid": true,
      "openDate": "2025-07-09T05:27:46.675Z",
      "pipValue": -1.0222222222222221,
      "pips": 18,
      "profitAndLoss": -18.4,
      "quantity": 0.1,
      "side": "Sell",
      "sl": 3294.76,
      "swap": 0,
      "symbol": "XAUUSD",
      "tp": 3246.17,
      "updatedAt": "2025-07-11T23:49:31.376Z",
      "id": "400984226",
      "date": "2025-07-09T05:27:46.675Z"
    },
    {
      "_id": "686df96c069059d2f0cfc4f4",
      "externalId": "400977194",
      "accountId": "25439044",
      "closeDate": "2025-07-09T05:27:33.807Z",
      "comment": "",
      "createdAt": "2025-07-09T05:09:00.629Z",
      "entry": 3296.02,
      "exit": 3292.35,
      "fee": -0.8,
      "invalidReasons": [],
      "isClosed": true,
      "isPartial": false,
      "isValid": true,
      "openDate": "2025-07-09T05:08:51.815Z",
      "pipValue": -2.0217983651226157,
      "pips": 36.7,
      "profitAndLoss": -74.2,
      "quantity": 0.2,
      "side": "Buy",
      "sl": 3290.93,
      "swap": 0,
      "symbol": "XAUUSD",
      "tp": 3306.6,
      "updatedAt": "2025-07-11T23:49:31.401Z",
      "id": "400977194",
      "date": "2025-07-09T05:08:51.815Z"
    },
    {
      "_id": "686df4bc069059d2f0cd86e2",
      "externalId": "400971694",
      "accountId": "25439044",
      "closeDate": "2025-07-09T05:27:33.806Z",
      "comment": "",
      "createdAt": "2025-07-09T04:49:00.698Z",
      "entry": 3296.51,
      "exit": 3292.35,
      "fee": -0.8,
      "invalidReasons": [],
      "isClosed": true,
      "isPartial": false,
      "isValid": true,
      "openDate": "2025-07-09T04:48:36.123Z",
      "pipValue": -2.019230769230769,
      "pips": 41.6,
      "profitAndLoss": -84,
      "quantity": 0.2,
      "side": "Buy",
      "sl": 3290.71,
      "swap": 0,
      "symbol": "XAUUSD",
      "tp": 3306.6,
      "updatedAt": "2025-07-11T23:49:31.396Z",
      "id": "400971694",
      "date": "2025-07-09T04:48:36.123Z"
    },
    {
      "_id": "686df4bc069059d2f0cd8707",
      "externalId": "400971692",
      "accountId": "25439044",
      "closeDate": "2025-07-09T05:27:33.795Z",
      "comment": "",
      "createdAt": "2025-07-09T04:49:00.703Z",
      "entry": 3296.48,
      "exit": 3292.35,
      "fee": -0.8,
      "invalidReasons": [],
      "isClosed": true,
      "isPartial": false,
      "isValid": true,
      "openDate": "2025-07-09T04:48:34.657Z",
      "pipValue": -2.019370460048426,
      "pips": 41.3,
      "profitAndLoss": -83.4,
      "quantity": 0.2,
      "side": "Buy",
      "sl": 3290.79,
      "swap": 0,
      "symbol": "XAUUSD",
      "tp": 0,
      "updatedAt": "2025-07-11T23:49:31.382Z",
      "id": "400971692",
      "date": "2025-07-09T04:48:34.657Z"
    },
    {
      "_id": "686df4bc069059d2f0cd86f7",
      "accountId": "25439044",
      "externalId": "400971688",
      "closeDate": "2025-07-09T05:27:33.794Z",
      "comment": "",
      "createdAt": "2025-07-09T04:49:00.701Z",
      "entry": 3296.5,
      "exit": 3292.35,
      "fee": -0.8,
      "invalidReasons": [],
      "isClosed": true,
      "isPartial": false,
      "isValid": true,
      "openDate": "2025-07-09T04:48:34.205Z",
      "pipValue": -2.019277108433735,
      "pips": 41.5,
      "profitAndLoss": -83.8,
      "quantity": 0.2,
      "side": "Buy",
      "sl": 3290.93,
      "swap": 0,
      "symbol": "XAUUSD",
      "tp": 3306.73,
      "updatedAt": "2025-07-11T23:49:31.413Z",
      "id": "400971688",
      "date": "2025-07-09T04:48:34.205Z"
    },
    {
      "_id": "686df3ea069059d2f0cd3beb",
      "externalId": "400971206",
      "accountId": "25439044",
      "closeDate": "2025-07-09T04:48:33.199Z",
      "comment": "",
      "createdAt": "2025-07-09T04:45:30.718Z",
      "entry": 3295.46,
      "exit": 3296.47,
      "fee": -0.8,
      "invalidReasons": [],
      "isClosed": true,
      "isPartial": false,
      "isValid": true,
      "openDate": "2025-07-09T04:45:24.040Z",
      "pipValue": -2.0792079207920793,
      "pips": 10.1,
      "profitAndLoss": -21,
      "quantity": 0.2,
      "side": "Sell",
      "sl": 0,
      "swap": 0,
      "symbol": "XAUUSD",
      "tp": 0,
      "updatedAt": "2025-07-11T23:49:31.395Z",
      "id": "400971206",
      "date": "2025-07-09T04:45:24.040Z"
    },
    {
      "_id": "686debd4069059d2f0c9e063",
      "accountId": "25439044",
      "externalId": "400964462",
      "closeDate": "2025-07-09T04:44:55.773Z",
      "comment": "",
      "createdAt": "2025-07-09T04:11:00.764Z",
      "entry": 3295.83,
      "exit": 3295.65,
      "fee": -0.8,
      "invalidReasons": [],
      "isClosed": true,
      "isPartial": false,
      "isValid": true,
      "openDate": "2025-07-09T04:10:43.951Z",
      "pipValue": -2.4444444444444446,
      "pips": 1.8,
      "profitAndLoss": -4.4,
      "quantity": 0.2,
      "side": "Buy",
      "sl": 3289.26,
      "swap": 0,
      "symbol": "XAUUSD",
      "tp": 0,
      "updatedAt": "2025-07-11T23:49:31.381Z",
      "id": "400964462",
      "date": "2025-07-09T04:10:43.951Z"
    },
    {
      "_id": "686debd4069059d2f0c9e19e",
      "accountId": "25439044",
      "externalId": "400964435",
      "closeDate": "2025-07-09T04:44:55.641Z",
      "comment": "",
      "createdAt": "2025-07-09T04:11:00.833Z",
      "entry": 3295.8,
      "exit": 3295.65,
      "fee": -0.8,
      "invalidReasons": [],
      "isClosed": true,
      "isPartial": false,
      "isValid": true,
      "openDate": "2025-07-09T04:10:33.055Z",
      "pipValue": -2.533333333333333,
      "pips": 1.5,
      "profitAndLoss": -3.8,
      "quantity": 0.2,
      "side": "Buy",
      "sl": 3288.79,
      "swap": 0,
      "symbol": "XAUUSD",
      "tp": 0,
      "updatedAt": "2025-07-11T23:49:31.391Z",
      "id": "400964435",
      "date": "2025-07-09T04:10:33.055Z"
    },
    {
      "_id": "686dd6a0069059d2f0bcd2ed",
      "accountId": "25439044",
      "externalId": "400928895",
      "closeDate": "2025-07-09T04:10:29.710Z",
      "comment": "",
      "createdAt": "2025-07-09T02:40:32.019Z",
      "entry": 3296.77,
      "exit": 3295.69,
      "fee": -0.8,
      "invalidReasons": [],
      "isClosed": true,
      "isPartial": false,
      "isValid": true,
      "openDate": "2025-07-09T02:40:21.016Z",
      "pipValue": -1.9259259259259258,
      "pips": -10.8,
      "profitAndLoss": 20.8,
      "quantity": 0.2,
      "side": "Sell",
      "sl": 3302.79,
      "swap": 0,
      "symbol": "XAUUSD",
      "tp": 3276.72,
      "updatedAt": "2025-07-11T23:49:31.400Z",
      "id": "400928895",
      "date": "2025-07-09T02:40:21.016Z"
    },
    {
      "_id": "686dd6a0069059d2f0bce294",
      "accountId": "25439044",
      "externalId": "400928665",
      "closeDate": "2025-07-09T04:10:29.709Z",
      "comment": "",
      "createdAt": "2025-07-09T02:40:32.969Z",
      "entry": 3296.95,
      "exit": 3295.69,
      "fee": -0.8,
      "invalidReasons": [],
      "isClosed": true,
      "isPartial": false,
      "isValid": true,
      "openDate": "2025-07-09T02:40:19.417Z",
      "pipValue": -1.9365079365079365,
      "pips": -12.6,
      "profitAndLoss": 24.4,
      "quantity": 0.2,
      "side": "Sell",
      "sl": 3302.79,
      "swap": 0,
      "symbol": "XAUUSD",
      "tp": 3276.59,
      "updatedAt": "2025-07-11T23:49:31.386Z",
      "id": "400928665",
      "date": "2025-07-09T02:40:19.417Z"
    },
    {
      "_id": "686dd374069059d2f0bb2e40",
      "accountId": "25439044",
      "externalId": "400924341",
      "closeDate": "2025-07-09T02:40:16.321Z",
      "comment": "",
      "createdAt": "2025-07-09T02:27:00.604Z",
      "entry": 3302.91,
      "exit": 3297.09,
      "fee": -0.2,
      "invalidReasons": [],
      "isClosed": true,
      "isPartial": false,
      "isValid": true,
      "openDate": "2025-07-09T02:26:55.240Z",
      "pipValue": -0.5034364261168385,
      "pips": 58.2,
      "profitAndLoss": -29.3,
      "quantity": 0.05,
      "side": "Buy",
      "sl": 0,
      "swap": 0,
      "symbol": "XAUUSD",
      "tp": 0,
      "updatedAt": "2025-07-11T23:49:31.408Z",
      "id": "400924341",
      "date": "2025-07-09T02:26:55.240Z"
    },
    {
      "_id": "686dcee2069059d2f0b944ba",
      "accountId": "25439044",
      "externalId": "400920184",
      "closeDate": "2025-07-09T02:40:16.320Z",
      "comment": "",
      "createdAt": "2025-07-09T02:07:30.596Z",
      "entry": 3302.39,
      "exit": 3297.09,
      "fee": -0.2,
      "invalidReasons": [],
      "isClosed": true,
      "isPartial": false,
      "isValid": true,
      "openDate": "2025-07-09T02:07:24.888Z",
      "pipValue": -0.5037735849056604,
      "pips": 53,
      "profitAndLoss": -26.7,
      "quantity": 0.05,
      "side": "Buy",
      "sl": 3292.5,
      "swap": 0,
      "symbol": "XAUUSD",
      "tp": 3324.53,
      "updatedAt": "2025-07-11T23:49:31.389Z",
      "id": "400920184",
      "date": "2025-07-09T02:07:24.888Z"
    },
    {
      "_id": "686dcc8a069059d2f0b816e7",
      "accountId": "25439044",
      "externalId": "400917346",
      "closeDate": "2025-07-09T02:40:16.320Z",
      "comment": "",
      "createdAt": "2025-07-09T01:57:30.854Z",
      "entry": 3303.46,
      "exit": 3297.09,
      "fee": -0.2,
      "invalidReasons": [],
      "isClosed": true,
      "isPartial": false,
      "isValid": true,
      "openDate": "2025-07-09T01:57:12.685Z",
      "pipValue": -0.5031397174254317,
      "pips": 63.7,
      "profitAndLoss": -32.05,
      "quantity": 0.05,
      "side": "Buy",
      "sl": 3292.5,
      "swap": 0,
      "symbol": "XAUUSD",
      "tp": 3324.62,
      "updatedAt": "2025-07-11T23:49:31.383Z",
      "id": "400917346",
      "date": "2025-07-09T01:57:12.685Z"
    },
    {
      "_id": "686dc276069059d2f0b2e640",
      "accountId": "25439044",
      "externalId": "400904250",
      "closeDate": "2025-07-09T02:40:16.309Z",
      "comment": "",
      "createdAt": "2025-07-09T01:14:30.661Z",
      "entry": 3302.22,
      "exit": 3297.09,
      "fee": -0.2,
      "invalidReasons": [],
      "isClosed": true,
      "isPartial": false,
      "isValid": true,
      "openDate": "2025-07-09T01:14:22.631Z",
      "pipValue": -0.5038986354775828,
      "pips": 51.3,
      "profitAndLoss": -25.85,
      "quantity": 0.05,
      "side": "Buy",
      "sl": 3292.59,
      "swap": 0,
      "symbol": "XAUUSD",
      "tp": 3324.62,
      "updatedAt": "2025-07-11T23:49:31.398Z",
      "id": "400904250",
      "date": "2025-07-09T01:14:22.631Z"
    },
    {
      "_id": "686cca42069059d2f0fae2c0",
      "accountId": "25439044",
      "externalId": "400402738",
      "closeDate": "2025-07-08T14:01:11.540Z",
      "comment": "",
      "createdAt": "2025-07-08T07:35:30.673Z",
      "entry": 3332.28,
      "exit": 3315.43,
      "fee": -0.4,
      "invalidReasons": [],
      "isClosed": true,
      "isPartial": false,
      "isValid": true,
      "openDate": "2025-07-08T07:35:19.551Z",
      "pipValue": -0.9976261127596439,
      "pips": -168.5,
      "profitAndLoss": 168.1,
      "quantity": 0.1,
      "side": "Sell",
      "sl": 3331.81,
      "swap": 0,
      "symbol": "XAUUSD",
      "tp": 3305.44,
      "updatedAt": "2025-07-11T23:49:31.406Z",
      "id": "400402738",
      "date": "2025-07-08T07:35:19.551Z"
    },
    {
      "_id": "686cc6be069059d2f0f6f651",
      "accountId": "25439044",
      "externalId": "400391864",
      "closeDate": "2025-07-08T14:01:11.539Z",
      "comment": "",
      "createdAt": "2025-07-08T07:20:30.950Z",
      "entry": 3336.23,
      "exit": 3315.43,
      "fee": -1.2,
      "invalidReasons": [],
      "isClosed": true,
      "isPartial": false,
      "isValid": true,
      "openDate": "2025-07-08T07:20:06.075Z",
      "pipValue": -2.994230769230769,
      "pips": -208,
      "profitAndLoss": 622.8,
      "quantity": 0.3,
      "side": "Sell",
      "sl": 3333.41,
      "swap": 0,
      "symbol": "XAUUSD",
      "tp": 3305.51,
      "updatedAt": "2025-07-11T23:49:31.397Z",
      "id": "400391864",
      "date": "2025-07-08T07:20:06.075Z"
    },
    {
      "_id": "686cc35a069059d2f0f388cf",
      "accountId": "25439044",
      "externalId": "400381716",
      "closeDate": "2025-07-08T07:20:02.258Z",
      "comment": "",
      "createdAt": "2025-07-08T07:06:02.074Z",
      "entry": 3338.28,
      "exit": 3336.21,
      "fee": -0.8,
      "invalidReasons": [],
      "isClosed": true,
      "isPartial": false,
      "isValid": true,
      "openDate": "2025-07-08T07:05:32.315Z",
      "pipValue": -2.038647342995169,
      "pips": 20.7,
      "profitAndLoss": -42.2,
      "quantity": 0.2,
      "side": "Buy",
      "sl": 3330.36,
      "swap": 0,
      "symbol": "XAUUSD",
      "tp": 3389.37,
      "updatedAt": "2025-07-11T23:49:31.418Z",
      "id": "400381716",
      "date": "2025-07-08T07:05:32.315Z"
    },
    {
      "_id": "686c9298069059d2f0d642b8",
      "externalId": "400305506",
      "accountId": "25439044",
      "closeDate": "2025-07-08T07:05:21.920Z",
      "comment": "",
      "createdAt": "2025-07-08T03:38:00.763Z",
      "entry": 3330.74,
      "exit": 3337.99,
      "fee": -0.6,
      "invalidReasons": [],
      "isClosed": true,
      "isPartial": false,
      "isValid": true,
      "openDate": "2025-07-08T03:37:54.318Z",
      "pipValue": -1.5082758620689654,
      "pips": 72.5,
      "profitAndLoss": -109.35,
      "quantity": 0.15,
      "side": "Sell",
      "sl": 0,
      "swap": 0,
      "symbol": "XAUUSD",
      "tp": 3314.77,
      "updatedAt": "2025-07-11T23:49:31.412Z",
      "id": "400305506",
      "date": "2025-07-08T03:37:54.318Z"
    },
    {
      "_id": "686c8beb069059d2f0d35fe4",
      "accountId": "25439044",
      "externalId": "400298645",
      "closeDate": "2025-07-08T07:05:21.919Z",
      "comment": "",
      "createdAt": "2025-07-08T03:09:31.286Z",
      "entry": 3331.82,
      "exit": 3337.99,
      "fee": -0.6,
      "invalidReasons": [],
      "isClosed": true,
      "isPartial": false,
      "isValid": true,
      "openDate": "2025-07-08T03:09:09.289Z",
      "pipValue": -1.5097244732576984,
      "pips": 61.7,
      "profitAndLoss": -93.15,
      "quantity": 0.15,
      "side": "Sell",
      "sl": 0,
      "swap": 0,
      "symbol": "XAUUSD",
      "tp": 3315.83,
      "updatedAt": "2025-07-11T23:49:31.391Z",
      "id": "400298645",
      "date": "2025-07-08T03:09:09.289Z"
    },
    {
      "_id": "686c563e069059d2f0b92d31",
      "accountId": "25439044",
      "externalId": "400236949",
      "closeDate": "2025-07-08T07:05:21.919Z",
      "comment": "",
      "createdAt": "2025-07-07T23:20:30.782Z",
      "entry": 3335.58,
      "exit": 3337.99,
      "fee": -0.6,
      "invalidReasons": [],
      "isClosed": true,
      "isPartial": false,
      "isValid": true,
      "openDate": "2025-07-07T23:20:26.988Z",
      "pipValue": -1.5248962655601659,
      "pips": 24.1,
      "profitAndLoss": -36.75,
      "quantity": 0.15,
      "side": "Sell",
      "sl": 3349.17,
      "swap": 0,
      "symbol": "XAUUSD",
      "tp": 3315.24,
      "updatedAt": "2025-07-11T23:49:31.389Z",
      "id": "400236949",
      "date": "2025-07-07T23:20:26.988Z"
    },
    {
      "_id": "686bbb16069059d2f050aad2",
      "accountId": "25439044",
      "externalId": "399952567",
      "closeDate": "2025-07-07T12:20:05.581Z",
      "comment": "[sl 3302.87]",
      "createdAt": "2025-07-07T12:18:30.793Z",
      "entry": 3304.93,
      "exit": 3302.77,
      "fee": -0.2,
      "invalidReasons": [],
      "isClosed": true,
      "isPartial": false,
      "isValid": true,
      "openDate": "2025-07-07T12:18:30.329Z",
      "pipValue": -0.5092592592592592,
      "pips": 21.6,
      "profitAndLoss": -11,
      "quantity": 0.05,
      "side": "Buy",
      "sl": 3302.87,
      "swap": 0,
      "symbol": "XAUUSD",
      "tp": 3330.39,
      "updatedAt": "2025-07-11T23:49:31.383Z",
      "id": "399952567",
      "date": "2025-07-07T12:18:30.329Z"
    },
    {
      "_id": "686bb6df069059d2f04db093",
      "accountId": "25439044",
      "externalId": "399944206",
      "closeDate": "2025-07-07T12:20:16.663Z",
      "comment": "[sl 3301.22]",
      "createdAt": "2025-07-07T12:00:31.000Z",
      "entry": 3302.88,
      "exit": 3301.16,
      "fee": -0.2,
      "invalidReasons": [],
      "isClosed": true,
      "isPartial": false,
      "isValid": true,
      "openDate": "2025-07-07T12:00:15.013Z",
      "pipValue": -0.5116279069767441,
      "pips": 17.2,
      "profitAndLoss": -8.8,
      "quantity": 0.05,
      "side": "Buy",
      "sl": 3301.22,
      "swap": 0,
      "symbol": "XAUUSD",
      "tp": 3330.39,
      "updatedAt": "2025-07-11T23:49:31.407Z",
      "id": "399944206",
      "date": "2025-07-07T12:00:15.013Z"
    },
    {
      "_id": "686bb40e069059d2f04b9554",
      "externalId": "399938476",
      "accountId": "25439044",
      "closeDate": "2025-07-07T11:57:44.503Z",
      "comment": "[sl 3301.26]",
      "createdAt": "2025-07-07T11:48:30.849Z",
      "entry": 3304.53,
      "exit": 3301.26,
      "fee": -1,
      "invalidReasons": [],
      "isClosed": true,
      "isPartial": false,
      "isValid": true,
      "openDate": "2025-07-07T11:48:16.280Z",
      "pipValue": -2.5305810397553516,
      "pips": 32.7,
      "profitAndLoss": -82.75,
      "quantity": 0.25,
      "side": "Buy",
      "sl": 3301.26,
      "swap": 0,
      "symbol": "XAUUSD",
      "tp": 0,
      "updatedAt": "2025-07-11T23:49:31.399Z",
      "id": "399938476",
      "date": "2025-07-07T11:48:16.280Z"
    },
    {
      "_id": "686bb40e069059d2f04b961a",
      "accountId": "25439044",
      "externalId": "399938419",
      "closeDate": "2025-07-07T11:57:47.053Z",
      "comment": "[sl 3301.23]",
      "createdAt": "2025-07-07T11:48:30.904Z",
      "entry": 3304.64,
      "exit": 3301.18,
      "fee": -1,
      "invalidReasons": [],
      "isClosed": true,
      "isPartial": false,
      "isValid": true,
      "openDate": "2025-07-07T11:48:11.129Z",
      "pipValue": -2.5289017341040463,
      "pips": 34.6,
      "profitAndLoss": -87.5,
      "quantity": 0.25,
      "side": "Buy",
      "sl": 3301.23,
      "swap": 0,
      "symbol": "XAUUSD",
      "tp": 0,
      "updatedAt": "2025-07-11T23:49:31.385Z",
      "id": "399938419",
      "date": "2025-07-07T11:48:11.129Z"
    },
    {
      "_id": "686ba401069059d2f03e99b2",
      "accountId": "25439044",
      "externalId": "399902547",
      "closeDate": "2025-07-07T11:48:09.361Z",
      "comment": "",
      "createdAt": "2025-07-07T10:40:01.055Z",
      "entry": 3304.33,
      "exit": 3304.57,
      "fee": -1,
      "invalidReasons": [],
      "isClosed": true,
      "isPartial": false,
      "isValid": true,
      "openDate": "2025-07-07T10:39:31.594Z",
      "pipValue": -2.916666666666667,
      "pips": 2.4,
      "profitAndLoss": -7,
      "quantity": 0.25,
      "side": "Sell",
      "sl": 3307.92,
      "swap": 0,
      "symbol": "XAUUSD",
      "tp": 3282.06,
      "updatedAt": "2025-07-11T23:49:31.400Z",
      "id": "399902547",
      "date": "2025-07-07T10:39:31.594Z"
    },
    {
      "_id": "686ba3e2069059d2f03e6cab",
      "accountId": "25439044",
      "externalId": "399902475",
      "closeDate": "2025-07-07T11:48:09.360Z",
      "comment": "",
      "createdAt": "2025-07-07T10:39:30.969Z",
      "entry": 3304.57,
      "exit": 3304.57,
      "fee": -1,
      "invalidReasons": [],
      "isClosed": true,
      "isPartial": false,
      "isValid": true,
      "openDate": "2025-07-07T10:39:28.403Z",
      "pipValue": 0,
      "pips": 0,
      "profitAndLoss": -1,
      "quantity": 0.25,
      "side": "Sell",
      "sl": 3307.9,
      "swap": 0,
      "symbol": "XAUUSD",
      "tp": 3281.92,
      "updatedAt": "2025-07-11T23:49:31.417Z",
      "id": "399902475",
      "date": "2025-07-07T10:39:28.403Z"
    }
  ]
}